plot_metric/functions.py
plot_metric-0.0.5.data/scripts/plot_metric_package
plot_metric-0.0.5.dist-info/LICENCE
plot_metric-0.0.5.dist-info/METADATA
plot_metric-0.0.5.dist-info/WHEEL
plot_metric-0.0.5.dist-info/top_level.txt
plot_metric-0.0.5.dist-info/RECORD
