Metadata-Version: 2.1
Name: plot-metric
Version: 0.0.5
Summary: A package with tools for plotting metrics
Home-page: https://github.com/yohann84L/plot_metric/
Author: Yohann Lereclus
Author-email: lereclus84L@gmail.com
License: UNKNOWN
Platform: UNKNOWN
Classifier: Programming Language :: Python :: 3
Classifier: License :: OSI Approved :: MIT License
Classifier: Operating System :: OS Independent
Requires-Dist: scipy (>=1.1.0)
Requires-Dist: matplotlib (>=3.0.2)
Requires-Dist: colorlover (>=0.3.0)
Requires-Dist: pandas (>=0.23.4)
Requires-Dist: seaborn (>=0.9.0)
Requires-Dist: numpy (>=1.15.4)
Requires-Dist: scikit-learn (>=0.21.2)
